{
  "sections": {
    "image_banner": {
      "type": "image-banner",
      "disabled": true,
      "blocks": {
        "heading": {
          "type": "heading",
          "settings": {
            "heading": "Image banner",
            "heading_size": "h0"
          }
        },
        "text": {
          "type": "text",
          "settings": {
            "text": "Give customers details about the banner image(s) or content on the template.",
            "text_style": "body"
          }
        },
        "button": {
          "type": "buttons",
          "settings": {
            "button_label_1": "Shop all",
            "button_link_1": "shopify:\/\/collections\/all",
            "button_style_secondary_1": true,
            "button_label_2": "",
            "button_link_2": "",
            "button_style_secondary_2": false
          }
        }
      },
      "block_order": [
        "heading",
        "text",
        "button"
      ],
      "settings": {
        "image_overlay_opacity": 40,
        "image_height": "large",
        "adapt_height_first_image": false,
        "desktop_content_position": "bottom-center",
        "show_text_box": false,
        "desktop_content_alignment": "center",
        "color_scheme": "background-1",
        "mobile_content_alignment": "center",
        "stack_images_on_mobile": false,
        "show_text_below": false
      }
    },
    "rich_text": {
      "type": "rich-text",
      "disabled": true,
      "blocks": {
        "heading": {
          "type": "heading",
          "settings": {
            "heading": "Talk about your brand",
            "heading_size": "h1"
          }
        },
        "text": {
          "type": "text",
          "settings": {
            "text": "<p>Share information about your brand with your customers. Describe a product, make announcements, or welcome customers to your store.<\/p>"
          }
        }
      },
      "block_order": [
        "heading",
        "text"
      ],
      "settings": {
        "color_scheme": "background-1",
        "full_width": true,
        "padding_top": 40,
        "padding_bottom": 0
      }
    },
    "featured_collection": {
      "type": "featured-collection",
      "disabled": true,
      "settings": {
        "title": "Featured products",
        "heading_size": "h2",
        "description": "",
        "show_description": false,
        "description_style": "body",
        "collection": "all",
        "products_to_show": 8,
        "columns_desktop": 4,
        "full_width": false,
        "show_view_all": false,
        "view_all_style": "solid",
        "enable_desktop_slider": false,
        "color_scheme": "background-1",
        "image_ratio": "adapt",
        "show_secondary_image": true,
        "show_vendor": false,
        "show_rating": false,
        "enable_quick_add": false,
        "columns_mobile": "2",
        "swipe_on_mobile": false,
        "padding_top": 28,
        "padding_bottom": 36
      }
    },
    "collage": {
      "type": "collage",
      "disabled": true,
      "blocks": {
        "collection-0": {
          "type": "collection",
          "settings": {
            "collection": ""
          }
        },
        "product": {
          "type": "product",
          "settings": {
            "product": "",
            "second_image": false
          }
        },
        "collection-1": {
          "type": "collection",
          "settings": {
            "collection": ""
          }
        }
      },
      "block_order": [
        "collection-0",
        "product",
        "collection-1"
      ],
      "settings": {
        "heading": "Multimedia collage",
        "heading_size": "h2",
        "desktop_layout": "left",
        "mobile_layout": "collage",
        "color_scheme": "background-1",
        "padding_top": 36,
        "padding_bottom": 36
      }
    },
    "video": {
      "type": "video",
      "disabled": true,
      "settings": {
        "heading": "",
        "heading_size": "h1",
        "video_url": "https:\/\/www.youtube.com\/watch?v=_9VUPq3SxOc",
        "description": "",
        "full_width": false,
        "color_scheme": "background-1",
        "padding_top": 36,
        "padding_bottom": 36
      }
    },
    "multicolumn": {
      "type": "multicolumn",
      "disabled": true,
      "blocks": {
        "column1": {
          "type": "column",
          "settings": {
            "title": "Column",
            "text": "<p>Pair text with an image to focus on your chosen product, collection, or blog post. Add details on availability, style, or even provide a review.<\/p>",
            "link_label": "",
            "link": ""
          }
        },
        "column2": {
          "type": "column",
          "settings": {
            "title": "Column",
            "text": "<p>Pair text with an image to focus on your chosen product, collection, or blog post. Add details on availability, style, or even provide a review.<\/p>",
            "link_label": "",
            "link": ""
          }
        },
        "column3": {
          "type": "column",
          "settings": {
            "title": "Column",
            "text": "<p>Pair text with an image to focus on your chosen product, collection, or blog post. Add details on availability, style, or even provide a review.<\/p>",
            "link_label": "",
            "link": ""
          }
        }
      },
      "block_order": [
        "column1",
        "column2",
        "column3"
      ],
      "settings": {
        "title": "",
        "heading_size": "h1",
        "image_width": "third",
        "image_ratio": "adapt",
        "columns_desktop": 3,
        "column_alignment": "center",
        "background_style": "none",
        "button_label": "",
        "button_link": "",
        "color_scheme": "background-1",
        "columns_mobile": "1",
        "swipe_on_mobile": false,
        "padding_top": 36,
        "padding_bottom": 36
      }
    },
    "1656147036ca2072a8": {
      "type": "image-banner-custom",
      "disabled": true,
      "blocks": {
        "165614703676a1478c-0": {
          "type": "heading",
          "settings": {
            "heading": "Enjoy This Winter Trend",
            "heading_size": "h1"
          }
        },
        "165614703676a1478c-1": {
          "type": "text",
          "settings": {
            "text": "Discover now latest collection",
            "text_style": "subtitle"
          }
        },
        "165614703676a1478c-2": {
          "type": "buttons",
          "settings": {
            "button_label_1": "Shop now",
            "button_link_1": "",
            "button_style_secondary_1": true,
            "button_label_2": "",
            "button_link_2": "",
            "button_style_secondary_2": false
          }
        }
      },
      "block_order": [
        "165614703676a1478c-0",
        "165614703676a1478c-1",
        "165614703676a1478c-2"
      ],
      "settings": {
        "image": "shopify:\/\/shop_images\/download_1.jpg",
        "image_2": "shopify:\/\/shop_images\/download.jpg",
        "image_overlay_opacity": 0,
        "image_height": "medium",
        "adapt_height_first_image": true,
        "desktop_content_position": "middle-right",
        "show_text_box": false,
        "desktop_content_alignment": "center",
        "color_scheme": "background-1",
        "mobile_content_alignment": "center",
        "stack_images_on_mobile": true,
        "show_text_below": false
      }
    },
    "16563864290650cf07": {
      "type": "slideshow",
      "disabled": true,
      "blocks": {
        "16563864296073a1ce-0": {
          "type": "slide",
          "settings": {
            "image": "shopify:\/\/shop_images\/download_1.jpg",
            "heading": "",
            "image_width": "100%",
            "heading_size": "h1",
            "subheading": "",
            "button_label": "New Arrivals",
            "link": "",
            "button_style_secondary": false,
            "box_align": "bottom-center",
            "show_text_box": false,
            "text_alignment": "center",
            "image_overlay_opacity": 0,
            "color_scheme": "background-1",
            "text_alignment_mobile": "center"
          }
        },
        "16563864296073a1ce-1": {
          "type": "slide",
          "settings": {
            "image": "shopify:\/\/shop_images\/download.jpg",
            "heading": "",
            "image_width": "50%",
            "heading_size": "h1",
            "subheading": "",
            "button_label": "Women Collection",
            "link": "",
            "button_style_secondary": false,
            "box_align": "bottom-center",
            "show_text_box": false,
            "text_alignment": "center",
            "image_overlay_opacity": 0,
            "color_scheme": "background-1",
            "text_alignment_mobile": "center"
          }
        },
        "eebf9fcc-5144-42f9-b76f-d67ec86d623d": {
          "type": "slide",
          "settings": {
            "image": "shopify:\/\/shop_images\/download_1.jpg",
            "heading": "",
            "image_width": "50%",
            "heading_size": "h1",
            "subheading": "",
            "button_label": "Men Collection",
            "link": "",
            "button_style_secondary": false,
            "box_align": "bottom-center",
            "show_text_box": false,
            "text_alignment": "center",
            "image_overlay_opacity": 0,
            "color_scheme": "background-1",
            "text_alignment_mobile": "center"
          }
        }
      },
      "block_order": [
        "16563864296073a1ce-0",
        "16563864296073a1ce-1",
        "eebf9fcc-5144-42f9-b76f-d67ec86d623d"
      ],
      "settings": {
        "layout": "full_bleed",
        "slide_height": "adapt_image",
        "slider_visual": "dots",
        "auto_rotate": true,
        "change_slides_speed": 3,
        "show_text_below": false,
        "accessibility_info": "Slideshow about our brand"
      }
    },
    "1656995444b28491a5": {
      "type": "slider",
      "blocks": {
        "1656995444c769f60c-0": {
          "type": "heading",
          "settings": {
            "heading": "Enjoy This Winter Trend",
            "heading_size": "Medium"
          }
        },
        "1656995444c769f60c-1": {
          "type": "text",
          "settings": {
            "text": "Discover now latest collections",
            "text_style": "body"
          }
        },
        "1656995444c769f60c-2": {
          "type": "buttons",
          "settings": {
            "button_label": "Shop Now",
            "button_link": ""
          }
        }
      },
      "block_order": [
        "1656995444c769f60c-0",
        "1656995444c769f60c-1",
        "1656995444c769f60c-2"
      ],
      "settings": {
        "image_1": "shopify:\/\/shop_images\/download_1.jpg",
        "image_2": "shopify:\/\/shop_images\/download.jpg",
        "image_overlay_opacity": 0,
        "banner_height": "medium",
        "desktop_content_position": "middle-center",
        "desktop_content_alignment": "center"
      }
    }
  },
  "order": [
    "image_banner",
    "rich_text",
    "featured_collection",
    "collage",
    "video",
    "multicolumn",
    "1656147036ca2072a8",
    "16563864290650cf07",
    "1656995444b28491a5"
  ]
}
